instabrade/__init__.py
instabrade/base.py
instabrade/decorators.py
instabrade/exceptions.py
instabrade/home_page.py
instabrade/instagram.py
instabrade/log_in_page.py
instabrade-0.0.7.dist-info/DESCRIPTION.rst
instabrade-0.0.7.dist-info/METADATA
instabrade-0.0.7.dist-info/RECORD
instabrade-0.0.7.dist-info/WHEEL
instabrade-0.0.7.dist-info/metadata.json
instabrade-0.0.7.dist-info/pbr.json
instabrade-0.0.7.dist-info/top_level.txt
