Metadata-Version: 2.0
Name: instabrade
Version: 0.0.7
Summary: Selenium based Instagram Scraper
Home-page: https://github.com/levi-rs/instabrade
Author: Levi Noecker
Author-email: levi.noecker@gmail.com
License: MIT
Keywords: instabrade instagram scrapper selenium pageobject page object
Platform: UNKNOWN
Classifier: Development Status :: 3 - Alpha
Classifier: Environment :: Console
Classifier: Intended Audience :: Developers
Classifier: License :: OSI Approved :: MIT License
Classifier: Operating System :: OS Independent
Classifier: Programming Language :: Python
Classifier: Programming Language :: Python :: 2
Classifier: Programming Language :: Python :: 2.7
Classifier: Programming Language :: Python :: 3
Classifier: Programming Language :: Python :: 3.4
Classifier: Programming Language :: Python :: 3.5
Classifier: Programming Language :: Python :: 3.6
Classifier: Programming Language :: Python :: Implementation :: CPython
Classifier: Programming Language :: Python :: Implementation :: PyPy
Requires-Dist: explicit (>=0.0.8)
Requires-Dist: pbr (>=2.0)
Requires-Dist: selenium
Requires-Dist: six
